{"name":"Ambiruptor","tagline":"The Ambiguation Interruptor","body":"### Introduction\r\n\r\nWelcome on the website of the **Ambiruptor project**. The [disambiguation problem](https://en.wikipedia.org/wiki/Word-sense_disambiguation) consist of finding the correct sense of an ambiguous word in a given sentence. Our target is to use learning models in order to be able to guess the correct meanings of words with the highest possible accuracy.\r\n\r\n### Installation\r\n\r\nThe **Ambiruptor project** uses **Python 3**. Here is a list of the packages to install :\r\n* numpy\r\n* nltk\r\n* scikit-learn\r\n\r\nIn order to download our tool you have to clone this repository.\r\n```\r\ngit clone git@github.com:Ambiruptor/Ambiruptor.git\r\n```\r\nThen just use the **Makefile** to download / compile the basics needed files.\r\n\r\n### License\r\n\r\nThe **Ambiruptor project** is available under the **GNU GLPv3** license. For more informations, look at the **LICENSE** file or consult www.gnu.org/licenses/gpl-3.0.html\r\n\r\n### Authors and Contributors\r\n* @Boritchev\r\n* @BRIKCI-SID-Boumediene\r\n* @eugeniashurko\r\n* @okupriianova\r\n* @Pouloud\r\n* @simon-mauras\r\n* @stendjaoui\r\n* @VuXuan\r\n\r\n### Support or Contact\r\nYou can contact us using the email adress <ambiruptor@ens-lyon.fr>.\r\n","google":"","note":"Don't delete this file! It's used internally to help with page regeneration."}